{
  "case": 63,
  "repeat": 1,
  "scenario": "TIGHT_GAP",
  "scenarioSeed": 5217400137194736569,
  "caseSeed": 206103874906143078,
  "scenarioVaried": false,
  "buyerStrategy": "FIXED_INCREMENT_2PCT",
  "dealerStrategy": "TIME_DEPENDENT_BOULWARE",
  "outcome": "DEAL",
  "acceptedBy": "DEALER",
  "roundsTaken": 10,
  "messageCount": 20,
  "askingPrice": 80000.0,
  "buyerFirstOffer": 62400.0,
  "buyerReservationPrice": 72800.0,
  "dealerReservationPrice": 71200.0,
  "finalPrice": 72800.0,
  "savingFromAsk": 7200.0,
  "savingPct": 9.0,
  "lastBuyerOffer": 72800.0,
  "lastDealerOffer": 72800.0,
  "buyerUtility": 0.0,
  "dealerUtility": 0.18181818181818182,
  "jointUtility": 0.18181818181818182,
  "agreementSurplus": 1600.0,
  "buyerSurplus": 0.0,
  "dealerProfit": 1600.0,
  "buyerDistanceFromReservation": 0.0,
  "dealerDistanceFromReservation": 1600.0,
  "buyerConcessionPct": 100.0,
  "dealerConcessionPct": 81.81818181818183,
  "benefitSide": "DEALER",
  "finalReason": "Round 10/10 | BOULWARE | Offer RM72800 vs RV RM71200 | lastRound\u003dtrue → COUNTER",
  "transcript": [
    {
      "round": 1,
      "actor": "BUYER",
      "action": "OFFER",
      "price": 62400.0,
      "reasoning": "Opening offer"
    },
    {
      "round": 1,
      "actor": "DEALER",
      "action": "OFFER",
      "price": 80000.0,
      "reasoning": "Round 1/10 | Curve\u003dBOULWARE β\u003d0.25 | Progress\u003d10% → Offer RM80000"
    },
    {
      "round": 2,
      "actor": "BUYER",
      "action": "OFFER",
      "price": 63600.0,
      "reasoning": "Round 1/10 | +2.0% increment | Offer RM62400 → RM63600 | RV ceiling: RM72800"
    },
    {
      "round": 2,
      "actor": "DEALER",
      "action": "OFFER",
      "price": 80000.0,
      "reasoning": "Round 2/10 | Curve\u003dBOULWARE β\u003d0.25 | Progress\u003d20% → Offer RM80000"
    },
    {
      "round": 3,
      "actor": "BUYER",
      "action": "OFFER",
      "price": 64900.0,
      "reasoning": "Round 2/10 | +2.0% increment | Offer RM63600 → RM64900 | RV ceiling: RM72800"
    },
    {
      "round": 3,
      "actor": "DEALER",
      "action": "OFFER",
      "price": 79900.0,
      "reasoning": "Round 3/10 | Curve\u003dBOULWARE β\u003d0.25 | Progress\u003d30% → Offer RM79900"
    },
    {
      "round": 4,
      "actor": "BUYER",
      "action": "OFFER",
      "price": 66200.0,
      "reasoning": "Round 3/10 | +2.0% increment | Offer RM64900 → RM66200 | RV ceiling: RM72800"
    },
    {
      "round": 4,
      "actor": "DEALER",
      "action": "OFFER",
      "price": 79800.0,
      "reasoning": "Round 4/10 | Curve\u003dBOULWARE β\u003d0.25 | Progress\u003d40% → Offer RM79800"
    },
    {
      "round": 5,
      "actor": "BUYER",
      "action": "OFFER",
      "price": 67500.0,
      "reasoning": "Round 4/10 | +2.0% increment | Offer RM66200 → RM67500 | RV ceiling: RM72800"
    },
    {
      "round": 5,
      "actor": "DEALER",
      "action": "OFFER",
      "price": 79500.0,
      "reasoning": "Round 5/10 | Curve\u003dBOULWARE β\u003d0.25 | Progress\u003d50% → Offer RM79500"
    },
    {
      "round": 6,
      "actor": "BUYER",
      "action": "OFFER",
      "price": 68900.0,
      "reasoning": "Round 5/10 | +2.0% increment | Offer RM67500 → RM68900 | RV ceiling: RM72800"
    },
    {
      "round": 6,
      "actor": "DEALER",
      "action": "OFFER",
      "price": 78900.0,
      "reasoning": "Round 6/10 | Curve\u003dBOULWARE β\u003d0.25 | Progress\u003d60% → Offer RM78900"
    },
    {
      "round": 7,
      "actor": "BUYER",
      "action": "OFFER",
      "price": 70300.0,
      "reasoning": "Round 6/10 | +2.0% increment | Offer RM68900 → RM70300 | RV ceiling: RM72800"
    },
    {
      "round": 7,
      "actor": "DEALER",
      "action": "OFFER",
      "price": 77900.0,
      "reasoning": "Round 7/10 | Curve\u003dBOULWARE β\u003d0.25 | Progress\u003d70% → Offer RM77900"
    },
    {
      "round": 8,
      "actor": "BUYER",
      "action": "OFFER",
      "price": 71700.0,
      "reasoning": "Round 7/10 | +2.0% increment | Offer RM70300 → RM71700 | RV ceiling: RM72800"
    },
    {
      "round": 8,
      "actor": "DEALER",
      "action": "OFFER",
      "price": 76400.0,
      "reasoning": "Round 8/10 | Curve\u003dBOULWARE β\u003d0.25 | Progress\u003d80% → Offer RM76400"
    },
    {
      "round": 9,
      "actor": "BUYER",
      "action": "OFFER",
      "price": 72800.0,
      "reasoning": "Round 8/10 | +2.0% increment | Offer RM71700 → RM72800 | RV ceiling: RM72800"
    },
    {
      "round": 9,
      "actor": "DEALER",
      "action": "OFFER",
      "price": 74200.0,
      "reasoning": "Round 9/10 | Curve\u003dBOULWARE β\u003d0.25 | Progress\u003d90% → Offer RM74200"
    },
    {
      "round": 10,
      "actor": "BUYER",
      "action": "OFFER",
      "price": 72800.0,
      "reasoning": "Round 9/10 | +2.0% increment | Offer RM72800 → RM72800 | RV ceiling: RM72800"
    },
    {
      "round": 10,
      "actor": "DEALER",
      "action": "ACCEPT",
      "price": 72800.0,
      "reasoning": "Round 10/10 | BOULWARE | Offer RM72800 vs RV RM71200 | lastRound\u003dtrue → COUNTER"
    }
  ]
}
