{
  "case": 87,
  "repeat": 1,
  "scenario": "WIDE_GAP",
  "scenarioSeed": 5217400152596663891,
  "caseSeed": 211356082194410528,
  "scenarioVaried": false,
  "buyerStrategy": "TIME_DEPENDENT_BOULWARE",
  "dealerStrategy": "TIME_DEPENDENT_BOULWARE",
  "outcome": "DEAL",
  "acceptedBy": "BUYER",
  "roundsTaken": 9,
  "messageCount": 20,
  "askingPrice": 80000.0,
  "buyerFirstOffer": 60800.0,
  "buyerReservationPrice": 82400.0,
  "dealerReservationPrice": 67200.0,
  "finalPrice": 71600.0,
  "savingFromAsk": 8400.0,
  "savingPct": 10.5,
  "lastBuyerOffer": 71600.0,
  "lastDealerOffer": 71600.0,
  "buyerUtility": 0.5,
  "dealerUtility": 0.34375,
  "jointUtility": 0.84375,
  "agreementSurplus": 15200.0,
  "buyerSurplus": 10800.0,
  "dealerProfit": 4400.0,
  "buyerDistanceFromReservation": 10800.0,
  "dealerDistanceFromReservation": 4400.0,
  "buyerConcessionPct": 50.0,
  "dealerConcessionPct": 65.625,
  "benefitSide": "BUYER",
  "finalReason": "Round 9/10 | Curve\u003dBOULWARE β\u003d0.25 | Progress\u003d90% → Offer RM75000",
  "transcript": [
    {
      "round": 1,
      "actor": "BUYER",
      "action": "OFFER",
      "price": 60800.0,
      "reasoning": "Opening offer"
    },
    {
      "round": 1,
      "actor": "DEALER",
      "action": "OFFER",
      "price": 80000.0,
      "reasoning": "Round 1/10 | Curve\u003dBOULWARE β\u003d0.25 | Progress\u003d10% → Offer RM80000"
    },
    {
      "round": 2,
      "actor": "BUYER",
      "action": "OFFER",
      "price": 60800.0,
      "reasoning": "Round 1/10 | Curve\u003dBOULWARE β\u003d0.25 | Progress\u003d10% → Offer RM60800"
    },
    {
      "round": 2,
      "actor": "DEALER",
      "action": "OFFER",
      "price": 80000.0,
      "reasoning": "Round 2/10 | Curve\u003dBOULWARE β\u003d0.25 | Progress\u003d20% → Offer RM80000"
    },
    {
      "round": 3,
      "actor": "BUYER",
      "action": "OFFER",
      "price": 60800.0,
      "reasoning": "Round 2/10 | Curve\u003dBOULWARE β\u003d0.25 | Progress\u003d20% → Offer RM60800"
    },
    {
      "round": 3,
      "actor": "DEALER",
      "action": "OFFER",
      "price": 79900.0,
      "reasoning": "Round 3/10 | Curve\u003dBOULWARE β\u003d0.25 | Progress\u003d30% → Offer RM79900"
    },
    {
      "round": 4,
      "actor": "BUYER",
      "action": "OFFER",
      "price": 61000.0,
      "reasoning": "Round 3/10 | Curve\u003dBOULWARE β\u003d0.25 | Progress\u003d30% → Offer RM61000"
    },
    {
      "round": 4,
      "actor": "DEALER",
      "action": "OFFER",
      "price": 79700.0,
      "reasoning": "Round 4/10 | Curve\u003dBOULWARE β\u003d0.25 | Progress\u003d40% → Offer RM79700"
    },
    {
      "round": 5,
      "actor": "BUYER",
      "action": "OFFER",
      "price": 61400.0,
      "reasoning": "Round 4/10 | Curve\u003dBOULWARE β\u003d0.25 | Progress\u003d40% → Offer RM61400"
    },
    {
      "round": 5,
      "actor": "DEALER",
      "action": "OFFER",
      "price": 79200.0,
      "reasoning": "Round 5/10 | Curve\u003dBOULWARE β\u003d0.25 | Progress\u003d50% → Offer RM79200"
    },
    {
      "round": 6,
      "actor": "BUYER",
      "action": "OFFER",
      "price": 62200.0,
      "reasoning": "Round 5/10 | Curve\u003dBOULWARE β\u003d0.25 | Progress\u003d50% → Offer RM62200"
    },
    {
      "round": 6,
      "actor": "DEALER",
      "action": "OFFER",
      "price": 78300.0,
      "reasoning": "Round 6/10 | Curve\u003dBOULWARE β\u003d0.25 | Progress\u003d60% → Offer RM78300"
    },
    {
      "round": 7,
      "actor": "BUYER",
      "action": "OFFER",
      "price": 63600.0,
      "reasoning": "Round 6/10 | Curve\u003dBOULWARE β\u003d0.25 | Progress\u003d60% → Offer RM63600"
    },
    {
      "round": 7,
      "actor": "DEALER",
      "action": "OFFER",
      "price": 76900.0,
      "reasoning": "Round 7/10 | Curve\u003dBOULWARE β\u003d0.25 | Progress\u003d70% → Offer RM76900"
    },
    {
      "round": 8,
      "actor": "BUYER",
      "action": "OFFER",
      "price": 66000.0,
      "reasoning": "Round 7/10 | Curve\u003dBOULWARE β\u003d0.25 | Progress\u003d70% → Offer RM66000"
    },
    {
      "round": 8,
      "actor": "DEALER",
      "action": "OFFER",
      "price": 74800.0,
      "reasoning": "Round 8/10 | Curve\u003dBOULWARE β\u003d0.25 | Progress\u003d80% → Offer RM74800"
    },
    {
      "round": 9,
      "actor": "BUYER",
      "action": "OFFER",
      "price": 69600.0,
      "reasoning": "Round 8/10 | Curve\u003dBOULWARE β\u003d0.25 | Progress\u003d80% → Offer RM69600"
    },
    {
      "round": 9,
      "actor": "DEALER",
      "action": "OFFER",
      "price": 71600.0,
      "reasoning": "Round 9/10 | Curve\u003dBOULWARE β\u003d0.25 | Progress\u003d90% → Offer RM71600"
    },
    {
      "round": 9,
      "actor": "BUYER",
      "action": "WOULD_ACCEPT",
      "price": 71600.0,
      "reasoning": "Counter would meet dealer offer; accepting dealer price."
    },
    {
      "round": 9,
      "actor": "BUYER",
      "action": "ACCEPT",
      "price": 71600.0,
      "reasoning": "Round 9/10 | Curve\u003dBOULWARE β\u003d0.25 | Progress\u003d90% → Offer RM75000"
    }
  ]
}
