{
  "case": 73,
  "repeat": 1,
  "scenario": "WIDE_GAP",
  "scenarioSeed": 5217400152596663891,
  "caseSeed": 211164966580415852,
  "scenarioVaried": false,
  "buyerStrategy": "BAYESIAN",
  "dealerStrategy": "BAYESIAN",
  "outcome": "DEAL",
  "acceptedBy": "BUYER",
  "roundsTaken": 2,
  "messageCount": 5,
  "askingPrice": 80000.0,
  "buyerFirstOffer": 60800.0,
  "buyerReservationPrice": 82400.0,
  "dealerReservationPrice": 67200.0,
  "finalPrice": 80000.0,
  "savingFromAsk": 0.0,
  "savingPct": 0.0,
  "lastBuyerOffer": 80000.0,
  "lastDealerOffer": 80000.0,
  "buyerUtility": 0.1111111111111111,
  "dealerUtility": 1.0,
  "jointUtility": 1.1111111111111112,
  "agreementSurplus": 15200.0,
  "buyerSurplus": 2400.0,
  "dealerProfit": 12800.0,
  "buyerDistanceFromReservation": 2400.0,
  "dealerDistanceFromReservation": 12800.0,
  "buyerConcessionPct": 88.88888888888889,
  "dealerConcessionPct": 0.0,
  "benefitSide": "DEALER",
  "finalReason": "Round 2/10 | β\u003d1.00 | Style\u003dUNKNOWN | AvgConcession\u003dRM0 (0.0%) | EstimatedFloor≈RM80000 | Offers seen\u003d2 → ACCEPT RM80000",
  "transcript": [
    {
      "round": 1,
      "actor": "BUYER",
      "action": "OFFER",
      "price": 60800.0,
      "reasoning": "Opening offer"
    },
    {
      "round": 1,
      "actor": "DEALER",
      "action": "OFFER",
      "price": 80000.0,
      "reasoning": "Round 1/10 | β\u003d1.00 | Style\u003dUNKNOWN | AvgConcession\u003dRM0 (0.0%) | EstimatedFloor≈RM0 | Offers seen\u003d1 → OFFER RM80000"
    },
    {
      "round": 2,
      "actor": "BUYER",
      "action": "OFFER",
      "price": 63000.0,
      "reasoning": "Round 1/10 | β\u003d1.00 | Style\u003dUNKNOWN | AvgConcession\u003dRM0 (0.0%) | EstimatedFloor≈RM0 | Offers seen\u003d1 → OFFER RM63000"
    },
    {
      "round": 2,
      "actor": "DEALER",
      "action": "OFFER",
      "price": 80000.0,
      "reasoning": "Round 2/10 | β\u003d1.00 | Style\u003dUNKNOWN | AvgConcession\u003dRM-2200 (0.0%) | EstimatedFloor≈RM65200 | Offers seen\u003d2 → OFFER RM80000"
    },
    {
      "round": 2,
      "actor": "BUYER",
      "action": "ACCEPT",
      "price": 80000.0,
      "reasoning": "Round 2/10 | β\u003d1.00 | Style\u003dUNKNOWN | AvgConcession\u003dRM0 (0.0%) | EstimatedFloor≈RM80000 | Offers seen\u003d2 → ACCEPT RM80000"
    }
  ]
}
